LICENSE.txt
MANIFEST.in
README.txt
setup.py
pcart_data_collections/__init__.py
pcart_data_collections/admin.py
pcart_data_collections/annotations.py
pcart_data_collections/apps.py
pcart_data_collections/cms_plugins.py
pcart_data_collections/forms.py
pcart_data_collections/lookups.py
pcart_data_collections/models.py
pcart_data_collections/urls.py
pcart_data_collections/views.py
pcart_data_collections.egg-info/PKG-INFO
pcart_data_collections.egg-info/SOURCES.txt
pcart_data_collections.egg-info/dependency_links.txt
pcart_data_collections.egg-info/not-zip-safe
pcart_data_collections.egg-info/requires.txt
pcart_data_collections.egg-info/top_level.txt
pcart_data_collections/locale/ru/LC_MESSAGES/django.mo
pcart_data_collections/locale/ru/LC_MESSAGES/django.po
pcart_data_collections/locale/uk/LC_MESSAGES/django.mo
pcart_data_collections/locale/uk/LC_MESSAGES/django.po
pcart_data_collections/migrations/0001_initial.py
pcart_data_collections/migrations/0002_auto_20171006_1125.py
pcart_data_collections/migrations/0003_datacollection_reversed_ordering.py
pcart_data_collections/migrations/0004_webformpluginmodel.py
pcart_data_collections/migrations/0005_auto_20171007_1720.py
pcart_data_collections/migrations/__init__.py
pcart_data_collections/templates/admin/data_collections/datacollection/datarecord_change.html
pcart_data_collections/templates/admin/data_collections/datacollection/datarecords_import.html
pcart_data_collections/templates/admin/data_collections/datacollection/datarecords_list.html
pcart_data_collections/templates/datacollections/_field_value.html
pcart_data_collections/templatetags/__init__.py
pcart_data_collections/templatetags/datacollections.py
pcart_data_collections/templatetags/expressions.py